{
  "marketing_stripe": {
    "text": "Miễn phí vận chuyển toàn quốc",
    "link": "/pages/cac-cau-hoi-thuong-gap"
  },
  "contacts_stripe": {
    "pages": [
      {
        "title": "xinchao@cytimy.com",
        "link": "mailto:xinchao@cytimy.com"
      },
      {
        "title": "Shop quần áo thời trang nam và nữ, và cho bé",
        "link": "/blog"
      }
    ],
    "phone_wpp": true,
    "socials": true
  },
  "categories_list": {
    "featured": [],
    "random": 6,
    "full_width": false
  },
  "search_input": true
}